LICENSE
MANIFEST.in
README.md
setup.cfg
setup.py
django_opening_hours_management.egg-info/PKG-INFO
django_opening_hours_management.egg-info/SOURCES.txt
django_opening_hours_management.egg-info/dependency_links.txt
django_opening_hours_management.egg-info/requires.txt
django_opening_hours_management.egg-info/top_level.txt
opening_hours_management/__init__.py
opening_hours_management/admin.py
opening_hours_management/apps.py
opening_hours_management/constants.py
opening_hours_management/fields.py
opening_hours_management/forms.py
opening_hours_management/models.py
opening_hours_management/shortcuts.py
opening_hours_management/widgets.py
opening_hours_management/conf/__init__.py
opening_hours_management/conf/settings.py
opening_hours_management/locale/fr/LC_MESSAGES/django.mo
opening_hours_management/locale/fr/LC_MESSAGES/django.po
opening_hours_management/migrations/0001_initial.py
opening_hours_management/migrations/0002_auto_20200402_1527.py
opening_hours_management/migrations/0003_auto_20200408_1214.py
opening_hours_management/migrations/0004_specificperiodhours_closure_reason.py
opening_hours_management/migrations/0005_auto_20200409_1256.py
opening_hours_management/migrations/0006_generalholidayshours_generalholidaystimerange.py
opening_hours_management/migrations/__init__.py
opening_hours_management/static/admin/css/openinghours_change_form.css
opening_hours_management/static/admin/js/RelatedOpeningHoursLookups.js
opening_hours_management/static/admin/js/opening_hours_popup_response.js
opening_hours_management/templates/admin/opening_hours_management/openinghours/change_form.html
opening_hours_management/templates/opening_hours_management/admin/openinghours/popup_response.html
opening_hours_management/templates/opening_hours_management/templatetags/opening_hours.html
opening_hours_management/templates/opening_hours_management/widgets/disabledselect.html
opening_hours_management/templates/opening_hours_management/widgets/opening_hours_widget.html
opening_hours_management/templates/opening_hours_management/widgets/selecttime.html
opening_hours_management/templatetags/__init__.py
opening_hours_management/templatetags/opening_hours_management.py